pubchem_api_crawler/__init__.py
pubchem_api_crawler/annotations.py
pubchem_api_crawler/config.py
pubchem_api_crawler/constants.py
pubchem_api_crawler/molecular_search.py
pubchem_api_crawler/rest_api.py
pubchem_api_crawler/utils.py
pubchem_api_crawler-1.0.3.dist-info/LICENSE
pubchem_api_crawler-1.0.3.dist-info/METADATA
pubchem_api_crawler-1.0.3.dist-info/WHEEL
pubchem_api_crawler-1.0.3.dist-info/RECORD
