Metadata-Version: 2.1
Name: pubchem-api-crawler
Version: 1.0.3
Summary: PubChem REST API crawler to retrieve compound properties using a molecular formula search
Home-page: https://github.com/jonasrenault/pubchem-api-crawler
License: MIT
Keywords: pubchem,crawler,chemistry,molecular-formula,data-mining
Author: Jonas Renault
Author-email: jonasrenault@gmail.com
Requires-Python: >=3.11,<4.0
Classifier: License :: OSI Approved :: MIT License
Classifier: Programming Language :: Python :: 3
Classifier: Programming Language :: Python :: 3.11
Classifier: Programming Language :: Python :: 3.12
Requires-Dist: pandas (>=2.2.0,<3.0.0)
Requires-Dist: pydantic-settings (>=2.1.0,<3.0.0)
Requires-Dist: ratelimit (>=2.2.1,<3.0.0)
Requires-Dist: requests (>=2.31.0,<3.0.0)
Requires-Dist: tqdm (>=4.66.1,<5.0.0)
Project-URL: Repository, https://github.com/jonasrenault/pubchem-api-crawler
